credit_card_info_generator/__init__.py
credit_card_info_generator/generator.py
credit_card_info_generator-1.0.dist-info/METADATA
credit_card_info_generator-1.0.dist-info/WHEEL
credit_card_info_generator-1.0.dist-info/top_level.txt
credit_card_info_generator-1.0.dist-info/RECORD
