Metadata-Version: 2.1
Name: credit-card-info-generator
Version: 1.0
Summary: Credit Card Info Generator is a Python package designed to create realistic dummy credit card data. It's a handy tool for developers who need to test payment systems, verify eCommerce applications, or any situation where real credit card data is not necessary or desirable.It supports a variety of card providers and generates corresponding credit card numbers, CVVs, and expiry dates.
Home-page: https://creditcardgenerator.app/
Author: Bellamy
Author-email: bellamyy.blakee100@gmail.com
License: UNKNOWN
Platform: UNKNOWN
Classifier: Programming Language :: Python :: 3
Classifier: License :: OSI Approved :: MIT License
Classifier: Operating System :: OS Independent
Requires-Python: >=3.6
